modela/Configuration.py
modela/ModelaException.py
modela/Resource.py
modela/__init__.py
modela/client.py
modela/common.py
modela/server.py
modela/util.py
modela/data/DataPipeline.py
modela/data/DataPipelineRun.py
modela/data/DataProduct.py
modela/data/DataProductVersion.py
modela/data/DataSource.py
modela/data/Dataset.py
modela/data/Entity.py
modela/data/Feature.py
modela/data/FeatureHistogram.py
modela/data/FeaturePipeline.py
modela/data/FeaturePipelineRun.py
modela/data/Featureset.py
modela/data/LabelingPipeline.py
modela/data/LabelingPipelineRun.py
modela/data/Recipe.py
modela/data/RecipeRun.py
modela/data/SqlQuery.py
modela/data/SqlQueryRun.py
modela/data/WebRequest.py
modela/data/WebRequestRun.py
modela/data/__init__.py
modela/data/common.py
modela/data/models.py
modela/inference/CronPrediction.py
modela/inference/Curtain.py
modela/inference/DataApp.py
modela/inference/InferenceService.py
modela/inference/Prediction.py
modela/inference/Predictor.py
modela/inference/__init__.py
modela/inference/common.py
modela/inference/models.py
modela/infra/Account.py
modela/infra/Alert.py
modela/infra/ApiToken.py
modela/infra/Attachment.py
modela/infra/Commit.py
modela/infra/Connection.py
modela/infra/FileService.py
modela/infra/Lab.py
modela/infra/License.py
modela/infra/ModelaSystem.py
modela/infra/Notifier.py
modela/infra/ServingSite.py
modela/infra/Tenant.py
modela/infra/UserRoleClass.py
modela/infra/VirtualBucket.py
modela/infra/VirtualCluster.py
modela/infra/VirtualVolume.py
modela/infra/__init__.py
modela/infra/common.py
modela/infra/connection_models.py
modela/infra/models.py
modela/team/Meeting.py
modela/team/PostMortem.py
modela/team/Review.py
modela/team/RunBook.py
modela/team/Todo.py
modela/team/__init__.py
modela/training/CronReport.py
modela/training/Model.py
modela/training/ModelAutobuilder.py
modela/training/ModelCompilerRun.py
modela/training/ModelPipeline.py
modela/training/ModelPipelineRun.py
modela/training/Notebook.py
modela/training/NotebookRun.py
modela-0.710.dist-info/AUTHORS.rst
modela-0.710.dist-info/LICENSE
modela-0.710.dist-info/METADATA
modela-0.710.dist-info/WHEEL
modela-0.710.dist-info/entry_points.txt
modela-0.710.dist-info/top_level.txt
modela-0.710.dist-info/RECORD
