Metadata-Version: 2.1
Name: modela
Version: 0.710
Summary: Modela Automatic Machine Learning SDK
Home-page: https://github.com/metaprov/modela-python-sdk
Author: Metaprov
Author-email: support@metaprov.com
License: Apache Software License 2.0
Keywords: modela
Platform: UNKNOWN
Classifier: Development Status :: 2 - Pre-Alpha
Classifier: Intended Audience :: Developers
Classifier: License :: OSI Approved :: Apache Software License
Classifier: Natural Language :: English
Classifier: Programming Language :: Python :: 3
Classifier: Programming Language :: Python :: 3.5
Classifier: Programming Language :: Python :: 3.6
Classifier: Programming Language :: Python :: 3.7
Classifier: Programming Language :: Python :: 3.8
Requires-Python: >=3.5
Requires-Dist: Click (>=7.0)
Requires-Dist: grpc-interceptor
Requires-Dist: grpcio
Requires-Dist: jwt
Requires-Dist: modelaapi (>=0.5.97)
Requires-Dist: pandas
Requires-Dist: protobuf
Requires-Dist: protoc-gen-swagger
Requires-Dist: tabulate
Requires-Dist: tqdm
Requires-Dist: typing-utils
